runesdb/__init__.py
runesdb/__main__.py
runesdb/main.py
runesdb/reader.py
runesdb/__pycache__/__init__.cpython-36.pyc
runesdb/__pycache__/__main__.cpython-36.pyc
runesdb/__pycache__/main.cpython-36.pyc
runesdb/__pycache__/reader.cpython-36.pyc
runesdb/tests/__init__.py
runesdb/tests/test_visualize.py
runesdb/tests/resources/runes_data_example.csv
runesdb-1.0.1.dist-info/LICENSE
runesdb-1.0.1.dist-info/METADATA
runesdb-1.0.1.dist-info/WHEEL
runesdb-1.0.1.dist-info/entry_points.txt
runesdb-1.0.1.dist-info/top_level.txt
runesdb-1.0.1.dist-info/RECORD
