Metadata-Version: 2.1
Name: runesdb
Version: 1.0.1
Summary: Parse RuneS DB exports
Home-page: https://github.com/clemsciences/old_norse_runes_db
Author: Clément Besnier
Author-email: clemsciences@aol.com
License: License :: OSI Approved :: MIT License
Platform: UNKNOWN
Classifier: Programming Language :: Python
Requires-Python: >=3.6
Requires-Dist: matplotlib
